json_api/__init__.py
json_api/errors.py
json_api/magic.py
json_api/magic_django.py
json_api/magic_sanic.py
json_api/middleware.py
json_api/signature.py
json_api/validate.py
json_api-0.1.22.dist-info/METADATA
json_api-0.1.22.dist-info/WHEEL
json_api-0.1.22.dist-info/top_level.txt
json_api-0.1.22.dist-info/RECORD
